babyweb/__init__.py
babyweb/config.py
babyweb/controller.py
babyweb/cron.py
babyweb/daemons.py
babyweb/logger.py
babyweb/mail.py
babyweb/memcache.py
babyweb/requesters.py
babyweb/response.py
babyweb/routes.py
babyweb/server.py
babyweb/shield.py
babyweb/sms.py
babyweb/version.py
babyweb/util/__init__.py
babyweb/util/converters.py
babyweb/util/loaders.py
babyweb/util/responders.py
babyweb/util/setters.py
babyweb-0.1.1.7.dist-info/LICENSE
babyweb-0.1.1.7.dist-info/METADATA
babyweb-0.1.1.7.dist-info/WHEEL
babyweb-0.1.1.7.dist-info/top_level.txt
babyweb-0.1.1.7.dist-info/RECORD
