Metadata-Version: 2.1
Name: babyweb
Version: 0.1.1.7
Summary: Basic Asynchronous weB librarY
Author: Mario Balibrera
Author-email: mario.balibrera@gmail.com
License: MIT License
Classifier: Development Status :: 3 - Alpha
Classifier: Environment :: Console
Classifier: Intended Audience :: Developers
Classifier: License :: OSI Approved :: MIT License
Classifier: Operating System :: OS Independent
Classifier: Programming Language :: Python
Classifier: Topic :: Software Development :: Libraries :: Python Modules
License-File: LICENSE
Requires-Dist: dez >=0.10.10.42
Requires-Dist: fyg >=0.1.7.8
Requires-Dist: requests >=2.28.1
